math_QBD/__init__.py
math_QBD/poisson.py
math_QBD-0.0.3.dist-info/LICENSE
math_QBD-0.0.3.dist-info/METADATA
math_QBD-0.0.3.dist-info/WHEEL
math_QBD-0.0.3.dist-info/top_level.txt
math_QBD-0.0.3.dist-info/RECORD
