Metadata-Version: 2.1
Name: math-QBD
Version: 0.0.3
Summary: Math support.
Home-page: https://github.com/QuantumBrainDisorder/math_QBD
Author: Rabarbar Batman
Author-email: 2rr@tuta.io
License: GPLv3
Project-URL: Source Code, https://github.com/QuantumBrainDisorder/math_QBD
Project-URL: Bug Tracker, https://github.com/QuantumBrainDisorder/math_QBD/issues
Keywords: math,numerical
Platform: UNKNOWN
Classifier: Programming Language :: Python :: 3.9
Classifier: Topic :: Scientific/Engineering
Classifier: Topic :: Scientific/Engineering
Classifier: Development Status :: 2 - Pre-Alpha
Classifier: License :: OSI Approved :: GNU General Public License v3 (GPLv3)
Classifier: Environment :: Console
Classifier: Intended Audience :: Science/Research
Classifier: Intended Audience :: Education
Classifier: Natural Language :: English
Requires-Python: >=3.9
